{"columns": ["Class", "Object count", "Avg area", "Max area", "Min area", "Min height", "Min height", "Max height", "Max height", "Avg height", "Avg height", "Min width", "Min width", "Max width", "Max width", "Avg width", "Avg width"], "columnsOptions": [{"type": "class"}, {"maxValue": 602}, {"postfix": "%", "tooltip": "Average object area in percents of all image."}, {"postfix": "%", "tooltip": "Maximum object area in percents of all image."}, {"postfix": "%", "tooltip": "Minimum object area in percents of all image."}, {"postfix": "px"}, {"postfix": "%", "tooltip": "Minimum object height in percents of image height."}, {"postfix": "px"}, {"postfix": "%", "tooltip": "Maximum object height in percents of image height."}, {"postfix": "px"}, {"postfix": "%", "tooltip": "Average object height in percents of image height."}, {"postfix": "px"}, {"postfix": "%", "tooltip": "Minimum object width in percents of image width."}, {"postfix": "px"}, {"postfix": "%", "tooltip": "Maximum object width in percents of image width."}, {"postfix": "px"}, {"postfix": "%", "tooltip": "Average object width in percents of image width."}], "data": [["apple", 546, 14.4, 44.22, 2.37, 532, 13.49, 2560, 84.66, 1219, 31.73, 531, 13.52, 2560, 84.66, 1267, 40.47], ["apple-bag", 357, 25.01, 66.15, 9.64, 995, 24.68, 3226, 96.59, 1667, 43.47, 996, 24.7, 3226, 96.59, 1774, 56.73], ["banana", 455, 25.97, 86.23, 9.98, 1025, 25.42, 3540, 98.21, 1779, 46.18, 1026, 25.45, 3539, 98.21, 1751, 55.78], ["banana-bag", 350, 29.75, 50.78, 11.86, 913, 24.7, 3020, 87.5, 1882, 48.93, 911, 24.7, 3020, 87.5, 1905, 60.79], ["blackberries", 140, 35.38, 92.06, 5.37, 776, 20.93, 3852, 99.24, 1981, 51.34, 776, 20.96, 3852, 99.24, 1889, 60.12], ["chili", 413, 13.87, 53.61, 2.02, 308, 7.64, 2758, 82.84, 1210, 31.56, 309, 7.66, 2758, 82.87, 1300, 41.6], ["chili-bag", 371, 20.79, 58.35, 4.82, 614, 15.23, 2969, 98.18, 1499, 38.98, 615, 15.25, 2969, 98.18, 1520, 48.5], ["grapes", 581, 16.18, 66.38, 0.21, 137, 3.4, 3002, 99.27, 1196, 31.17, 138, 3.42, 3002, 99.27, 1273, 40.71], ["grapes-bag", 350, 20.63, 61.36, 9.94, 765, 20.46, 2994, 99.01, 1475, 38.67, 764, 20.49, 2994, 99.01, 1726, 55.4], ["lemon", 588, 14.67, 94.91, 1.01, 295, 7.32, 3974, 99.24, 1167, 30.37, 296, 7.34, 3974, 99.24, 1189, 37.95], ["lemon-bag", 343, 15.59, 44.84, 5.54, 676, 16.77, 2552, 84.39, 1301, 33.95, 677, 16.79, 2552, 84.39, 1396, 44.65], ["raspberry", 175, 45.33, 93.3, 4.16, 664, 16.47, 3926, 98.02, 2277, 59.01, 665, 16.49, 3926, 98.02, 2177, 69.28], ["tomato", 602, 13.79, 51.16, 0.82, 263, 8.53, 2896, 95.77, 1111, 29.09, 262, 8.53, 2896, 95.77, 1266, 40.58], ["tomato-bag", 357, 28.45, 80.34, 8.76, 926, 22.97, 3264, 99.24, 1759, 45.84, 927, 22.99, 3264, 99.24, 1860, 59.44]], "options": {"fixColumns": 1, "sort": {"columnIndex": 1, "order": "desc"}, "pageSize": 10}}